gcl_looper/__init__.py
gcl_looper/version.py
gcl_looper/services/__init__.py
gcl_looper/services/base.py
gcl_looper/services/basic.py
gcl_looper/services/bjoern_service.py
gcl_looper/services/hub.py
gcl_looper/tests/__init__.py
gcl_looper/tests/functional/__init__.py
gcl_looper/tests/functional/services/__init__.py
gcl_looper/tests/functional/services/test_basic.py
gcl_looper/tests/functional/services/test_bjoern.py
gcl_looper/tests/functional/services/test_hub.py
gcl_looper/tests/unit/__init__.py
gcl_looper/tests/unit/services/__init__.py
gcl_looper/tests/unit/services/test_basic.py
gcl_looper-1.0.1.dist-info/licenses/AUTHORS
gcl_looper-1.0.1.dist-info/licenses/LICENSE
gcl_looper-1.0.1.dist-info/METADATA
gcl_looper-1.0.1.dist-info/WHEEL
gcl_looper-1.0.1.dist-info/pbr.json
gcl_looper-1.0.1.dist-info/top_level.txt
gcl_looper-1.0.1.dist-info/RECORD
