Metadata-Version: 2.4
Name: gcl_looper
Version: 1.0.1
Summary: Looper is a daemonizer library, it can help you with lifecycle of your daemon.
Home-page: https://github.com/infraguys/gcl_looper
Author: Genesis Corporation
Author-email: mail@gmelikov.ru
Classifier: Intended Audience :: Developers
Classifier: License :: OSI Approved :: Apache Software License
Classifier: Operating System :: POSIX :: Linux
Classifier: Programming Language :: Python
Classifier: Programming Language :: Python :: 3
Classifier: Programming Language :: Python :: 3.8
Classifier: Programming Language :: Python :: 3.10
Classifier: Programming Language :: Python :: 3.11
Classifier: Programming Language :: Python :: 3.12
Classifier: Programming Language :: Python :: 3.13
License-File: LICENSE
License-File: AUTHORS
Requires-Dist: pbr<5.8.1,>=1.10.0
Requires-Dist: setuptools<76.0.0,>=75.3.0
Dynamic: author
Dynamic: author-email
Dynamic: classifier
Dynamic: description
Dynamic: home-page
Dynamic: license-file
Dynamic: requires-dist
Dynamic: summary
